DE/__init__.py
DE/rest.py
testDE_sumit0790-0.0.1.dist-info/LICENSE
testDE_sumit0790-0.0.1.dist-info/METADATA
testDE_sumit0790-0.0.1.dist-info/WHEEL
testDE_sumit0790-0.0.1.dist-info/top_level.txt
testDE_sumit0790-0.0.1.dist-info/RECORD
