Metadata-Version: 2.1
Name: testDE-sumit0790
Version: 0.0.1
Summary: Sample test package for DE APIs POC
Home-page: UNKNOWN
Author: Sumit Sharma
Author-email: sharmasumit64@gmail.com
License: UNKNOWN
Platform: UNKNOWN
Classifier: Programming Language :: Python :: 3
Classifier: Operating System :: OS Independent
Requires-Python: >=3.6
